plugin.py
hatch_command_version-1.0.1.dist-info/METADATA
hatch_command_version-1.0.1.dist-info/WHEEL
hatch_command_version-1.0.1.dist-info/entry_points.txt
hatch_command_version-1.0.1.dist-info/top_level.txt
hatch_command_version-1.0.1.dist-info/RECORD
