Metadata-Version: 2.4
Name: hatch-command-version
Version: 1.0.1
Summary: A version source plugin to the hatchling.build python build backend that obtains a version by running a command.
Author-email: Matt McShane <matt@mattmcshane.com>
Project-URL: Repository, https://github.com/mmcshane/hatch-command-version
Keywords: hatch,hatchling,version
Requires-Dist: hatchling>=1.27.0
